edd/__init__.py
edd/edd.py
esdl/__init__.py
esdl/_version.py
esdl/ecore_documentation.py
esdl/esdl.py
esdl/esdl_handler.py
esdl/support_functions.py
esdl/edr/__init__.py
esdl/edr/client.py
esdl/geometry/__init__.py
esdl/geometry/shape.py
esdl/profiles/__init__.py
esdl/profiles/excelprofilemanager.py
esdl/profiles/influxdbprofilemanager.py
esdl/profiles/profilemanager.py
esdl/resources/__init__.py
esdl/resources/json.py
esdl/resources/xmi.py
esdl/resources/xmlresource.py
esdl/units/__init__.py
esdl/units/conversion.py
esdl/units/parser.py
esdl/utils/__init__.py
esdl/utils/datetime_utils.py
pyesdl-25.12.1.dist-info/licenses/LICENSE.md
pyesdl-25.12.1.dist-info/METADATA
pyesdl-25.12.1.dist-info/WHEEL
pyesdl-25.12.1.dist-info/top_level.txt
pyesdl-25.12.1.dist-info/RECORD
