Metadata-Version: 2.4
Name: pyESDL
Version: 25.12.1
Summary: Python implementation of the Energy System Description Language (ESDL) for modelling energy systems
Home-page: https://energytransition.gitbook.io/esdl/
Author: Ewoud Werkman
Author-email: ewoud.werkman@tno.nl
License: Apache 2.0
Requires-Python: >=3.7
License-File: LICENSE.md
Requires-Dist: pyecore==0.13.2
Provides-Extra: profiles
Requires-Dist: influxdb==5.3.1; extra == "profiles"
Requires-Dist: openpyxl==3.1.2; extra == "profiles"
Provides-Extra: geometry
Requires-Dist: shapely==2.0.1; extra == "geometry"
Requires-Dist: geojson==3.1.0; extra == "geometry"
Requires-Dist: pyproj==3.6.1; extra == "geometry"
Provides-Extra: all
Requires-Dist: influxdb==5.3.1; extra == "all"
Requires-Dist: openpyxl==3.1.2; extra == "all"
Requires-Dist: shapely==2.0.1; extra == "all"
Requires-Dist: geojson==3.1.0; extra == "all"
Requires-Dist: pyproj==3.6.1; extra == "all"
Dynamic: author
Dynamic: author-email
Dynamic: description
Dynamic: description-content-type
Dynamic: home-page
Dynamic: license
Dynamic: license-file
Dynamic: provides-extra
Dynamic: requires-dist
Dynamic: requires-python
Dynamic: summary
